personio_py/__init__.py
personio_py/client.py
personio_py/errors.py
personio_py/mapping.py
personio_py/models.py
personio_py/search.py
personio_py/version.py
personio_py-0.2.3.dist-info/LICENSE
personio_py-0.2.3.dist-info/METADATA
personio_py-0.2.3.dist-info/WHEEL
personio_py-0.2.3.dist-info/top_level.txt
personio_py-0.2.3.dist-info/RECORD
