Metadata-Version: 2.1
Name: personio-py
Version: 0.2.3
Summary: a lightweight Personio API client
Home-page: https://github.com/at-gmbh/personio-py
Author: Sebastian Straub
Author-email: sebastian.straub@alexanderthamm.com
License: Apache 2.0
Project-URL: Documentation, https://at-gmbh.github.io/personio-py/
Project-URL: Source, https://github.com/at-gmbh/personio-py
Project-URL: Tracker, https://github.com/at-gmbh/personio-py/issues
Platform: any
Classifier: License :: OSI Approved :: Apache Software License
Classifier: Development Status :: 4 - Beta
Classifier: Intended Audience :: Developers
Classifier: Topic :: Internet :: WWW/HTTP
Classifier: Topic :: Office/Business
Classifier: Topic :: Software Development :: Libraries :: Python Modules
Classifier: Typing :: Typed
Classifier: Programming Language :: Python
Classifier: Programming Language :: Python :: 3
Classifier: Programming Language :: Python :: 3 :: Only
Classifier: Programming Language :: Python :: 3.7
Classifier: Programming Language :: Python :: 3.8
Classifier: Programming Language :: Python :: 3.9
Requires-Python: >=3.7
Requires-Dist: requests (<3.0.0,>=2.21.0)
